LICENCE
dfi/__init__.py
dfi/client.py
dfi/connect.py
dfi/errors.py
dfi/models/__init__.py
dfi/models/filters/__init__.py
dfi/models/filters/filter_fields.py
dfi/models/filters/geometry/__init__.py
dfi/models/filters/geometry/bbox.py
dfi/models/filters/geometry/point.py
dfi/models/filters/geometry/polygon.py
dfi/models/filters/only.py
dfi/models/filters/time_range.py
dfi/models/query_document.py
dfi/models/returns/__init__.py
dfi/models/returns/count.py
dfi/models/returns/records.py
dfi/services/__init__.py
dfi/services/datasets.py
dfi/services/identities.py
dfi/services/info.py
dfi/services/ingest.py
dfi/services/query.py
dfi/services/users.py
dfipy-9.1.0.dist-info/LICENCE
dfipy-9.1.0.dist-info/METADATA
dfipy-9.1.0.dist-info/WHEEL
dfipy-9.1.0.dist-info/RECORD
