Metadata-Version: 2.1
Name: dfipy
Version: 9.1.0
Summary: Python SDK targeting the DFI API
Home-page: https://www.generalsystem.com/
Author: Robert Edwards
Author-email: robert.edwards@generalsystem.com
Maintainer: General System
Requires-Python: >=3.10,<4.0
Classifier: Programming Language :: Python :: 3
Classifier: Programming Language :: Python :: 3.10
Classifier: Programming Language :: Python :: 3.11
Classifier: Programming Language :: Python :: 3.12
Requires-Dist: boto3 (>=1.34.19,<2.0.0)
Requires-Dist: natsort (>=8.4.0,<9.0.0)
Requires-Dist: pandas (>=2.0.1,<3.0.0)
Requires-Dist: pyarrow (>=15.0.2,<16.0.0)
Requires-Dist: requests (>=2.30.0,<3.0.0)
Requires-Dist: sseclient-py (>=1.7.2,<2.0.0)
Requires-Dist: tqdm (>=4.65.0,<5.0.0)
Requires-Dist: typing-extensions (>=4.10.0,<5.0.0)
Project-URL: Documentation, https://dfipy.docs.generalsystem.com/
Project-URL: Repository, https://github.com/thegeneralsystem/dfipy
